ezbee/__init__.py
ezbee/__main__.py
ezbee/cmat2html.py
ezbee/color_map.py
ezbee/common_prefix.py
ezbee/detect.py
ezbee/ezbee.py
ezbee/gen_filename.py
ezbee/gen_pairs.py
ezbee/loadtext.py
ezbee/loglevel.py
ezbee/save_xlsx_tsv_csv.py
ezbee/text2lists.py
ezbee-0.1.5.dist-info/entry_points.txt
ezbee-0.1.5.dist-info/LICENSE
ezbee-0.1.5.dist-info/WHEEL
ezbee-0.1.5.dist-info/METADATA
ezbee-0.1.5.dist-info/RECORD
